hysteron_tgraphs/__init__.py
hysteron_tgraphs/candidategraphs.py
hysteron_tgraphs/graph_analysis.py
hysteron_tgraphs/model.py
hysteron_tgraphs/parametrizations.py
hysteron_tgraphs/plotting.py
hysteron_tgraphs/polyhedron_analysis.py
hysteron_tgraphs-2.0.0.dist-info/WHEEL
hysteron_tgraphs-2.0.0.dist-info/METADATA
hysteron_tgraphs-2.0.0.dist-info/RECORD
