Metadata-Version: 2.4
Name: hysteron-tgraphs
Version: 2.0.0
Author: Margot Teunisse
License-Expression: MIT
Requires-Dist: numpy>=1.26.4
Requires-Dist: scipy>=1.13.1
Requires-Dist: networkx>=3.3 ; extra == 'graph-analysis'
Requires-Dist: matplotlib>=3.9.2 ; extra == 'plotting'
Requires-Dist: pycddlib==2.1.8.post1 ; extra == 'polyhedron-analysis'
Requires-Python: >=3.12
Provides-Extra: graph-analysis
Provides-Extra: plotting
Provides-Extra: polyhedron-analysis
